MANIFEST.in
README
setup.py
rsa4py/__init__.py
rsa4py.egg-info/PKG-INFO
rsa4py.egg-info/SOURCES.txt
rsa4py.egg-info/dependency_links.txt
rsa4py.egg-info/requires.txt
rsa4py.egg-info/top_level.txt
rsa4py/src/rsa.cpp
rsa4py/src/src/rsa.cpp
rsa4py/src/rsa.cpp
rsa4py/src/rsa.pxd
rsa4py/src/rsa.pyx
rsa4py/src/rsa_cppInter.pxd
rsa4py/src/src/rsa.cpp
rsa4py/src/src/rsa.h